python_resumable/__init__.py
python_resumable/uploader.py
python_resumable/models/__init__.py
python_resumable/models/chunk.py
python_resumable/models/repository.py
python_resumable-0.1.2.dist-info/DESCRIPTION.rst
python_resumable-0.1.2.dist-info/METADATA
python_resumable-0.1.2.dist-info/RECORD
python_resumable-0.1.2.dist-info/WHEEL
python_resumable-0.1.2.dist-info/metadata.json
python_resumable-0.1.2.dist-info/top_level.txt
