Metadata-Version: 2.0
Name: python-resumable
Version: 0.1.2
Summary: Hook for working with resumable.js
Home-page: https://github.com/Reriiru/python-resumable
Author: Igor Velme <ivelmey@gmail.com>, Andrey Kasatov
Author-email: ivelmey@gmail.com
License: MIT
Keywords: resumablejs
Platform: UNKNOWN
Requires-Python: >=3
Requires-Dist: natsort
